Tool.py
trackerao/__init__.py
trackerao/tracker.py
trackerao-1.5.7.dist-info/METADATA
trackerao-1.5.7.dist-info/WHEEL
trackerao-1.5.7.dist-info/top_level.txt
trackerao-1.5.7.dist-info/RECORD
