Metadata-Version: 2.1
Name: trackerao
Version: 1.5.7
Summary: this package is made to track ants
Home-page: https://github.com/Dennis-Ning/Tracker_ao
Author: Dennis Ning
Author-email: 274399033@qq.com
License: MIT
Platform: UNKNOWN
